alt_legibilidade/__init__.py
alt_legibilidade/__main__.py
alt_legibilidade/cli.py
alt_legibilidade/extrair_texto.py
alt_legibilidade/frases.py
alt_legibilidade/letras.py
alt_legibilidade/palavras.py
alt_legibilidade/palavrasComplexas.py
alt_legibilidade/silabas.py
alt_legibilidade/banco/palavras-mais-comuns-utf8.txt
alt_legibilidade-0.1.2.dist-info/licenses/LICENSE
alt_legibilidade-0.1.2.dist-info/METADATA
alt_legibilidade-0.1.2.dist-info/WHEEL
alt_legibilidade-0.1.2.dist-info/entry_points.txt
alt_legibilidade-0.1.2.dist-info/top_level.txt
alt_legibilidade-0.1.2.dist-info/RECORD
