Metadata-Version: 2.4
Name: alt-legibilidade
Version: 0.1.2
Summary: Ferramenta para análise de legibilidade de textos em português
Home-page: https://github.com/marcopolomoreno/alt-python
Author: Equipe ALT
Author-email: marcopolo@unir.br
License: MIT
Classifier: Programming Language :: Python :: 3
Classifier: License :: OSI Approved :: MIT License
Classifier: Operating System :: OS Independent
Classifier: Natural Language :: Portuguese
Requires-Python: >=3.7
License-File: LICENSE
Requires-Dist: pymupdf
Requires-Dist: python-docx
Dynamic: author
Dynamic: author-email
Dynamic: classifier
Dynamic: description
Dynamic: description-content-type
Dynamic: home-page
Dynamic: license
Dynamic: license-file
Dynamic: requires-dist
Dynamic: requires-python
Dynamic: summary
